nightflight/__init__.py
nightflight/airport_nvecs.py
nightflight/airports.txt.bz2
nightflight/make_locations.py
nightflight/night.py
nightflight-0.9.1.dist-info/LICENSE
nightflight-0.9.1.dist-info/METADATA
nightflight-0.9.1.dist-info/WHEEL
nightflight-0.9.1.dist-info/top_level.txt
nightflight-0.9.1.dist-info/RECORD
