Metadata-Version: 2.1
Name: nightflight
Version: 0.9.1
Summary: Calculate night flying hours
Home-page: https://github.com/JonHurst/nightflight
Author: Jon Hurst
Author-email: jon.a@hursts.org.uk
Classifier: Development Status :: 4 - Beta
Classifier: Programming Language :: Python :: 3
Classifier: License :: OSI Approved :: GNU General Public License v3 or later (GPLv3+)
Classifier: Operating System :: OS Independent
Requires-Python: >=3.11
License-File: LICENSE
Requires-Dist: astral >=2.2
